aidk_core/__init__.py
aidk_core/ai_dev_kit.py
aidk_core/data.py
aidk_core/deep_rnn.py
aidk_core/deep_rnnFast.py
aidk_core/default_network.py
aidk_core/gan.py
aidk_core/network.py
aidk_core/networkFast.py
aidk_core/neuralnet_module.py
aidk_core/neuromorphic_nn.py
aidk_core/prediction_module.py
aidk_core/probmax.py
aidk_core/resnet.py
aidk_core/resnetFast.py
aidk_core/rfcn.py
aidk_core/rfcnFast.py
aidk_core/token_manager.py
aidk_core/tranformers_module.py
aidk_core/words.txt
aidk_core-1.0.0.dist-info/METADATA
aidk_core-1.0.0.dist-info/WHEEL
aidk_core-1.0.0.dist-info/top_level.txt
aidk_core-1.0.0.dist-info/RECORD
