Metadata-Version: 2.4
Name: aidk_core
Version: 1.0.0
Summary: Artificial Intelligence Development Kit (AIDK) – unified, production-grade AI framework
Author: Akshansh Nandan
Author-email: Akshansh Nandan <microcodehack@gmail.com>
License: GNU General Public License
Project-URL: Homepage, https://github.com/Akshansh-Nandan/Tech/tree/AI/AI_lib
Project-URL: Documentation, https://github.com/Akshansh-Nandan/Tech/tree/AI/AI_lib
Project-URL: Source, https://github.com/Akshansh-Nandan/Tech/tree/AI/AI_lib
Keywords: artificial-intelligence,machine-learning,deep-learning,neural-networks,transformers,meta-learning
Classifier: Development Status :: 5 - Production/Stable
Classifier: Intended Audience :: Developers
Classifier: Topic :: Scientific/Engineering :: Artificial Intelligence
Classifier: Programming Language :: Python :: 3
Classifier: Programming Language :: Python :: 3.10
Classifier: Operating System :: POSIX :: Linux
Classifier: License :: Other/Proprietary License
Requires-Python: ==3.10.*
Requires-Dist: absl-py==2.3.1
Requires-Dist: aiohappyeyeballs==2.6.1
Requires-Dist: aiohttp==3.13.2
Requires-Dist: aiosignal==1.4.0
Requires-Dist: argcomplete==3.6.3
Requires-Dist: asteval==0.9.33
Requires-Dist: astunparse==1.6.3
Requires-Dist: async-timeout==5.0.1
Requires-Dist: attrs==25.4.0
Requires-Dist: bitsandbytes==0.49.0
Requires-Dist: boto==2.49.0
Requires-Dist: cachetools==5.5.2
Requires-Dist: certifi==2025.11.12
Requires-Dist: cffi==2.0.0
Requires-Dist: charset-normalizer==3.4.4
Requires-Dist: clarabel==0.11.1
Requires-Dist: click==8.3.1
Requires-Dist: cloudpickle==3.1.2
Requires-Dist: contourpy==1.3.2
Requires-Dist: crcmod==1.7
Requires-Dist: cryptography==43.0.3
Requires-Dist: cvxpy==1.7.5
Requires-Dist: cycler==0.12.1
Requires-Dist: exceptiongroup==1.3.1
Requires-Dist: fasteners==0.20
Requires-Dist: filelock==3.20.1
Requires-Dist: flatbuffers==25.12.19
Requires-Dist: fonttools==4.61.1
Requires-Dist: frozenlist==1.8.0
Requires-Dist: fsspec==2025.12.0
Requires-Dist: gast==0.7.0
Requires-Dist: gcs-oauth2-boto-plugin==3.3
Requires-Dist: google-apitools==0.5.35
Requires-Dist: google-auth==2.39.0
Requires-Dist: google-auth-httplib2==0.3.0
Requires-Dist: google-pasta==0.2.0
Requires-Dist: google-reauth==0.1.1
Requires-Dist: grpcio==1.76.0
Requires-Dist: gsutil==5.35
Requires-Dist: gym==0.26.2
Requires-Dist: gym-notices==0.1.0
Requires-Dist: h5py==3.15.1
Requires-Dist: hf-xet==1.2.0
Requires-Dist: httplib2==0.20.4
Requires-Dist: huggingface-hub==0.36.0
Requires-Dist: idna==3.11
Requires-Dist: iniconfig==2.3.0
Requires-Dist: Jinja2==3.1.6
Requires-Dist: joblib==1.5.3
Requires-Dist: keras==3.12.0
Requires-Dist: kiwisolver==1.4.9
Requires-Dist: lava-dl==0.6.0
Requires-Dist: lava-nc==0.10.0
Requires-Dist: learn2learn==0.2.0
Requires-Dist: libclang==18.1.1
Requires-Dist: linecache2==1.0.0
Requires-Dist: llvmlite==0.46.0
Requires-Dist: Markdown==3.10
Requires-Dist: markdown-it-py==4.0.0
Requires-Dist: MarkupSafe==3.0.3
Requires-Dist: matplotlib==3.10.8
Requires-Dist: mdurl==0.1.2
Requires-Dist: mixture-of-experts==0.2.3
Requires-Dist: ml_dtypes==0.5.4
Requires-Dist: monotonic==1.6
Requires-Dist: mpmath==1.3.0
Requires-Dist: multidict==6.7.0
Requires-Dist: namex==0.1.0
Requires-Dist: networkx==2.8.7
Requires-Dist: ninja==1.13.0
Requires-Dist: nltk==3.9.2
Requires-Dist: numba==0.63.1
Requires-Dist: numpy==1.26.4
Requires-Dist: nvidia-cublas-cu12==12.1.3.1
Requires-Dist: nvidia-cuda-cupti-cu12==12.1.105
Requires-Dist: nvidia-cuda-nvrtc-cu12==12.1.105
Requires-Dist: nvidia-cuda-runtime-cu12==12.1.105
Requires-Dist: nvidia-cudnn-cu12==9.1.0.70
Requires-Dist: nvidia-cufft-cu12==11.0.2.54
Requires-Dist: nvidia-cufile-cu12==1.13.1.3
Requires-Dist: nvidia-curand-cu12==10.3.2.106
Requires-Dist: nvidia-cusolver-cu12==11.4.5.107
Requires-Dist: nvidia-cusparse-cu12==12.1.0.106
Requires-Dist: nvidia-cusparselt-cu12==0.6.2
Requires-Dist: nvidia-nccl-cu12==2.21.5
Requires-Dist: nvidia-nvjitlink-cu12==12.4.127
Requires-Dist: nvidia-nvshmem-cu12==3.3.20
Requires-Dist: nvidia-nvtx-cu12==12.1.105
Requires-Dist: oauth2client==4.1.3
Requires-Dist: opencv-python-headless==4.11.0.86
Requires-Dist: opt_einsum==3.4.0
Requires-Dist: optree==0.18.0
Requires-Dist: osqp==1.0.5
Requires-Dist: packaging==25.0
Requires-Dist: pandas==2.3.3
Requires-Dist: pillow==10.4.0
Requires-Dist: pluggy==1.6.0
Requires-Dist: propcache==0.4.1
Requires-Dist: protobuf==6.33.2
Requires-Dist: pyasn1==0.6.1
Requires-Dist: pyasn1_modules==0.4.2
Requires-Dist: pycparser==2.23
Requires-Dist: Pygments==2.19.2
Requires-Dist: pyOpenSSL==24.2.1
Requires-Dist: pyparsing==3.3.1
Requires-Dist: pytest==7.4.4
Requires-Dist: python-dateutil==2.9.0.post0
Requires-Dist: pytz==2025.2
Requires-Dist: pyu2f==0.1.5
Requires-Dist: PyYAML==6.0.3
Requires-Dist: qpth==0.0.18
Requires-Dist: regex==2025.11.3
Requires-Dist: requests==2.32.5
Requires-Dist: retry-decorator==1.1.1
Requires-Dist: rich==14.2.0
Requires-Dist: rsa==4.7.2
Requires-Dist: safetensors==0.7.0
Requires-Dist: scikit-learn==1.7.2
Requires-Dist: scipy==1.15.3
Requires-Dist: scs==3.2.10
Requires-Dist: sentence-transformers==5.2.0
Requires-Dist: sentencepiece==0.2.1
Requires-Dist: six==1.17.0
Requires-Dist: sympy==1.13.1
Requires-Dist: tensorboard==2.20.0
Requires-Dist: tensorboard-data-server==0.7.2
Requires-Dist: tensorflow==2.20.0
Requires-Dist: termcolor==3.3.0
Requires-Dist: tf_keras==2.20.1
Requires-Dist: threadpoolctl==3.6.0
Requires-Dist: tiktoken==0.12.0
Requires-Dist: tokenizers==0.22.1
Requires-Dist: tomli==2.3.0
Requires-Dist: torch==2.5.1+cu121
Requires-Dist: torchaudio==2.5.1+cu121
Requires-Dist: torchvision==0.20.1+cu121
Requires-Dist: tqdm==4.67.1
Requires-Dist: traceback2==1.4.0
Requires-Dist: transformers==4.57.3
Requires-Dist: triton==3.1.0
Requires-Dist: typing_extensions==4.15.0
Requires-Dist: tzdata==2025.3
Requires-Dist: unittest2==1.1.0
Requires-Dist: urllib3==2.6.2
Requires-Dist: Werkzeug==3.1.4
Requires-Dist: wrapt==2.0.1
Requires-Dist: yarl==1.22.0
